Hello123/__init__.py
Hello123/etho.py
Samplehello-0.0.9.dist-info/METADATA
Samplehello-0.0.9.dist-info/WHEEL
Samplehello-0.0.9.dist-info/top_level.txt
Samplehello-0.0.9.dist-info/RECORD
