Metadata-Version: 2.1
Name: Samplehello
Version: 0.0.9
Summary: This is sn sample project
Home-page: https://github.com/BhuvaneshRs/SamplePypi
Author: Bhuvanesh
Author-email: Bhuvaneshwararagavendra@gmail.com
Project-URL: Bug Tracker, https://github.com/BhuvaneshRs/SamplePypi/issues
Classifier: Programming Language :: Python :: 3
Classifier: License :: OSI Approved :: MIT License
Classifier: Operating System :: OS Independent
Requires-Python: >=3.6
